BengaliPlagiarismChecker/__init__.py
BengaliPlagiarismChecker/corpus.db
BengaliPlagiarismCheckerTool-0.0.3.dist-info/LICENSE
BengaliPlagiarismCheckerTool-0.0.3.dist-info/METADATA
BengaliPlagiarismCheckerTool-0.0.3.dist-info/WHEEL
BengaliPlagiarismCheckerTool-0.0.3.dist-info/top_level.txt
BengaliPlagiarismCheckerTool-0.0.3.dist-info/RECORD
