Metadata-Version: 2.1
Name: BengaliPlagiarismCheckerTool
Version: 0.0.3
Summary: A package for plagiarism detection on Bengali texts.
Home-page: https://github.com/SATYAJIT1910/Bengali-Plagiarism-Checker-pip
Author: Satyajit Ghosh
Author-email: satyajit.ghosh@outlook.in
Project-URL: Bug Tracker, https://github.com/SATYAJIT1910/Bengali-Plagiarism-Checker-pip/issues
Classifier: Programming Language :: Python :: 3
Classifier: License :: OSI Approved
Classifier: Operating System :: OS Independent
Classifier: Natural Language :: Bengali
Requires-Python: >=3.6
License-File: LICENSE
